nds/__init__.py
nds/ndomsort.py
nds/stools.py
nds-0.4.3.dist-info/LICENSE
nds-0.4.3.dist-info/METADATA
nds-0.4.3.dist-info/WHEEL
nds-0.4.3.dist-info/top_level.txt
nds-0.4.3.dist-info/RECORD
