Metadata-Version: 2.1
Name: nds
Version: 0.4.3
Summary: Non-dominated sorting algorithm.
Home-page: https://github.com/KernelA/nds-py
Author: Alexander Kryuchkov
Author-email: KernelA@users.noreply.github.com
License: MIT
Project-URL: Bug Tracker, https://github.com/KernelA/nds-py/issues
Keywords: nds,multiobjective-optimization,non-dominated-sorting
Platform: UNKNOWN
Classifier: Development Status :: 5 - Production/Stable
Classifier: Intended Audience :: Developers
Classifier: Operating System :: OS Independent
Classifier: License :: OSI Approved :: MIT License
Classifier: Programming Language :: Python :: 3
Classifier: Programming Language :: Python :: Implementation
Requires-Python: >=3.6
